cnpgen/__init__.py
cnpgen/__main__.py
cnp_generator-1.1.1.dist-info/LICENSE
cnp_generator-1.1.1.dist-info/METADATA
cnp_generator-1.1.1.dist-info/WHEEL
cnp_generator-1.1.1.dist-info/top_level.txt
cnp_generator-1.1.1.dist-info/RECORD
