Metadata-Version: 2.1
Name: cnp-generator
Version: 1.1.1
Summary: Romania CNP number generator and decoder.
Home-page: https://github.com/myshy93/cnp-generator
Author: Mihai Dinu
Author-email: mihai.dinu93@gmail.com
License: MIT
Keywords: cnp romania generator decoder
Platform: UNKNOWN
Classifier: Programming Language :: Python :: 3
Classifier: License :: OSI Approved :: MIT License
Classifier: Operating System :: OS Independent
Requires-Python: >=3.6
